pytest_ckan/__init__.py
pytest_ckan/fixtures.py
pytest_ckan/plugin.py
pytest_ckan-0.0.12.dist-info/COPYING
pytest_ckan-0.0.12.dist-info/METADATA
pytest_ckan-0.0.12.dist-info/WHEEL
pytest_ckan-0.0.12.dist-info/entry_points.txt
pytest_ckan-0.0.12.dist-info/top_level.txt
pytest_ckan-0.0.12.dist-info/RECORD
