Metadata-Version: 2.1
Name: pytest-ckan
Version: 0.0.12
Summary: Backport of CKAN 2.9 pytest plugin and fixtures to CAKN 2.8
Home-page: https://github.com/datopian/pytest-ckan
Author: Shahar Evron
Author-email: shahar.evron@datopian.com
License: MIT
Keywords: ckan,pytest
Platform: UNKNOWN
Classifier: Framework :: Pytest
Classifier: Programming Language :: Python :: 2
Classifier: Programming Language :: Python :: 3
Classifier: Development Status :: 4 - Beta
Classifier: License :: OSI Approved :: MIT License
